pubchem_api/__init__.py
pubchem_api/api_get_data.py
pubchem_api/cli.py
pubchem_api/pubchem_api.py
pubchem_api-1.0.1.dist-info/AUTHORS.rst
pubchem_api-1.0.1.dist-info/LICENSE
pubchem_api-1.0.1.dist-info/METADATA
pubchem_api-1.0.1.dist-info/WHEEL
pubchem_api-1.0.1.dist-info/entry_points.txt
pubchem_api-1.0.1.dist-info/top_level.txt
pubchem_api-1.0.1.dist-info/RECORD
