Metadata-Version: 2.1
Name: pubchem-api
Version: 1.0.1
Summary: A simple API call to the pubchem database
Home-page: https://github.com/simonholmes001/pubchem_api
Author: simonholmes001
Author-email: simonholmesabc@gmail.com
License: MIT license
Keywords: pubchem_api
Platform: UNKNOWN
Classifier: Development Status :: 2 - Pre-Alpha
Classifier: Intended Audience :: Developers
Classifier: License :: OSI Approved :: MIT License
Classifier: Natural Language :: English
Classifier: Programming Language :: Python :: 3
Classifier: Programming Language :: Python :: 3.5
Classifier: Programming Language :: Python :: 3.6
Classifier: Programming Language :: Python :: 3.7
Classifier: Programming Language :: Python :: 3.8
Requires-Python: >=3.5
Requires-Dist: Click (>=7.0)
Requires-Dist: requests
